{
  "db_name": "PostgreSQL",
  "query": "\n        select submitter_id, country_id, question, kind, question_asset_id\n        from poll_submissions where id = $1 and status = 'pending_admin' for update\n        ",
  "describe": {
    "columns": [
      {
        "ordinal": 0,
        "name": "submitter_id",
        "type_info": "Int8",
        "origin": {
          "Table": {
            "table": "poll_submissions",
            "name": "submitter_id"
          }
        }
      },
      {
        "ordinal": 1,
        "name": "country_id",
        "type_info": "Int8",
        "origin": {
          "Table": {
            "table": "poll_submissions",
            "name": "country_id"
          }
        }
      },
      {
        "ordinal": 2,
        "name": "question",
        "type_info": "Text",
        "origin": {
          "Table": {
            "table": "poll_submissions",
            "name": "question"
          }
        }
      },
      {
        "ordinal": 3,
        "name": "kind",
        "type_info": "Text",
        "origin": {
          "Table": {
            "table": "poll_submissions",
            "name": "kind"
          }
        }
      },
      {
        "ordinal": 4,
        "name": "question_asset_id",
        "type_info": "Int8",
        "origin": {
          "Table": {
            "table": "poll_submissions",
            "name": "question_asset_id"
          }
        }
      }
    ],
    "parameters": {
      "Left": [
        "Int8"
      ]
    },
    "nullable": [
      false,
      false,
      false,
      false,
      true
    ]
  },
  "hash": "a836712148f83b94304d478c9ae9828d270bb30a5beeab29ca49f169dc8c10f0"
}
